inotify_simple.py
inotify_simple-2.0.0.dist-info/licenses/LICENSE
inotify_simple-2.0.0.dist-info/METADATA
inotify_simple-2.0.0.dist-info/WHEEL
inotify_simple-2.0.0.dist-info/top_level.txt
inotify_simple-2.0.0.dist-info/RECORD
