Metadata-Version: 2.4
Name: inotify-simple
Version: 2.0.0
Summary: A simple wrapper around inotify. No fancy bells and whistles, just a literal wrapper with ctypes. Under 100 lines of code!
Author-email: Chris Billington <chrisjbillington@gmail.com>
License-Expression: BSD-2-Clause
Project-URL: Repository, https://github.com/chrisjbillington/inotify_simple.git
Project-URL: Documentation, http://inotify-simple.readthedocs.io/
Project-URL: Issues, https://github.com/chrisjbillington/inotify_simple/issues
Keywords: inotify
Requires-Python: >=3.6
License-File: LICENSE
Dynamic: license-file
